gitlogfeed.py
gitlogfeed-1.1.1.dist-info/LICENSE
gitlogfeed-1.1.1.dist-info/METADATA
gitlogfeed-1.1.1.dist-info/WHEEL
gitlogfeed-1.1.1.dist-info/entry_points.txt
gitlogfeed-1.1.1.dist-info/top_level.txt
gitlogfeed-1.1.1.dist-info/RECORD
